{
  "main": {
    "id": "6e464d26c9bfd1ce",
    "type": "split",
    "children": [
      {
        "id": "f37998890811947c",
        "type": "tabs",
        "children": [
          {
            "id": "83e5fe24cb8fe9ae",
            "type": "leaf",
            "state": {
              "type": "markdown",
              "state": {
                "file": "高效率工作者的36個生活訣竅/工作方法/專注.md",
                "mode": "source",
                "source": true
              }
            }
          }
        ]
      }
    ],
    "direction": "vertical"
  },
  "left": {
    "id": "9407156f0bcce53a",
    "type": "split",
    "children": [
      {
        "id": "5bc9480397eb2d07",
        "type": "tabs",
        "children": [
          {
            "id": "9aa58c9f02e83b30",
            "type": "leaf",
            "state": {
              "type": "file-explorer",
              "state": {
                "sortOrder": "alphabetical"
              }
            }
          },
          {
            "id": "0496d3457e8bf5f4",
            "type": "leaf",
            "state": {
              "type": "search",
              "state": {
                "query": "",
                "matchingCase": false,
                "explainSearch": false,
                "collapseAll": false,
                "extraContext": false,
                "sortOrder": "alphabetical"
              }
            }
          },
          {
            "id": "e0eb16accf9c61fa",
            "type": "leaf",
            "state": {
              "type": "bookmarks",
              "state": {}
            }
          }
        ]
      }
    ],
    "direction": "horizontal",
    "width": 300
  },
  "right": {
    "id": "c1bccbb9e10e33bc",
    "type": "split",
    "children": [
      {
        "id": "3659becbca097c71",
        "type": "tabs",
        "children": [
          {
            "id": "81238e578cdeaccf",
            "type": "leaf",
            "state": {
              "type": "backlink",
              "state": {
                "file": "高效率工作者的36個生活訣竅/工作方法/專注.md",
                "collapseAll": false,
                "extraContext": false,
                "sortOrder": "alphabetical",
                "showSearch": false,
                "searchQuery": "",
                "backlinkCollapsed": false,
                "unlinkedCollapsed": true
              }
            }
          },
          {
            "id": "3a05b3d80427b1ae",
            "type": "leaf",
            "state": {
              "type": "outgoing-link",
              "state": {
                "file": "高效率工作者的36個生活訣竅/工作方法/專注.md",
                "linksCollapsed": false,
                "unlinkedCollapsed": true
              }
            }
          },
          {
            "id": "eb9b949bf5cff7d7",
            "type": "leaf",
            "state": {
              "type": "tag",
              "state": {
                "sortOrder": "frequency",
                "useHierarchy": true
              }
            }
          },
          {
            "id": "2d51b13682c23640",
            "type": "leaf",
            "state": {
              "type": "outline",
              "state": {
                "file": "高效率工作者的36個生活訣竅/工作方法/專注.md"
              }
            }
          }
        ]
      }
    ],
    "direction": "horizontal",
    "width": 200
  },
  "left-ribbon": {
    "hiddenItems": {
      "switcher:開啟快速切換": false,
      "graph:查看關聯圖": false,
      "canvas:建立新畫布": false,
      "daily-notes:開啟今天的每日筆記": false,
      "templates:插入模板": false,
      "command-palette:開啟命令面板": false,
      "workspaces:管理工作區配置": false
    }
  },
  "active": "83e5fe24cb8fe9ae",
  "lastOpenFiles": [
    "高效率工作者的36個生活訣竅/工作方法/借力使力.md",
    "高效率工作者的36個生活訣竅/工作方法/專注.md",
    "高效率工作者的36個生活訣竅/工作方法/灰色思考.md",
    "高效率工作者的36個生活訣竅/工作方法/30%的不確定性原則.md",
    "高效率工作者的36個生活訣竅/工作方法/必要項和加分項.md",
    "高效率工作者的36個生活訣竅/工作方法/溫水煮青蛙.md",
    "高效率工作者的36個生活訣竅/工作方法/聰明邀功.md",
    "高效率工作者的36個生活訣竅/工作方法/提問.md",
    "高效率工作者的36個生活訣竅/核心思維/正向思維.md",
    "高效率工作者的36個生活訣竅/心態/被討厭的勇氣.md",
    "高效率工作者的36個生活訣竅/核心思維/富人心態.md",
    "高效率工作者的36個生活訣竅/心態/重啟新局.md",
    "高效率工作者的36個生活訣竅/心態/無限賽局.md",
    "高效率工作者的36個生活訣竅/心態/休耕期.md",
    "高效率工作者的36個生活訣竅/心態/善用工具.md",
    "高效率工作者的36個生活訣竅/心態/風險與機會.md",
    "高效率工作者的36個生活訣竅/核心思維/脈絡思考.md",
    "高效率工作者的36個生活訣竅/核心思維/內部歸因.md",
    "高效率工作者的36個生活訣竅/核心思維/長線思維.md",
    "高效率工作者的36個生活訣竅/核心思維/原則.md",
    "高效率工作者的36個生活訣竅/心態/接受不完美.md",
    "高效率工作者的36個生活訣竅/工作方法/主動出擊，爭取機會.md",
    "高效率工作者的36個生活訣竅/工作方法/有效努力.md",
    "高效率工作者的36個生活訣竅/心態",
    "高效率工作者的36個生活訣竅/工作方法",
    "高效率工作者的36個生活訣竅/核心思維",
    "高效率工作者的36個生活訣竅/關係經營",
    "高效率工作者的36個生活訣竅/自我管理",
    "高效率工作者的36個生活訣竅"
  ]
}